alpha_mini_rug/__init__.py
alpha_mini_rug/aruco.py
alpha_mini_rug/camera_services.py
alpha_mini_rug/follow_face.py
alpha_mini_rug/keywords.py
alpha_mini_rug/movements.py
alpha_mini_rug/smart_q.py
alpha_mini_rug/speech_to_text.py
alpha_mini_rug-0.6.0.dist-info/METADATA
alpha_mini_rug-0.6.0.dist-info/WHEEL
alpha_mini_rug-0.6.0.dist-info/top_level.txt
alpha_mini_rug-0.6.0.dist-info/RECORD
